CHANGES.txt
LICENSE.txt
MANIFEST.in
README.md
requirements-dev.txt
requirements-docs.txt
requirements.txt
setup.py
docs/alternatives_api.rst
docs/api.rst
docs/cli.rst
docs/index.rst
docs/intro.rst
docs/_build/html/_sources/alternatives_api.txt
docs/_build/html/_sources/api.txt
docs/_build/html/_sources/cmd.txt
docs/_build/html/_sources/cmd_pywizard.txt
docs/_build/html/_sources/index.txt
docs/_build/html/_sources/install_recipie.txt
docs/_build/html/_sources/intro.txt
docs/_build/html/_sources/module.txt
docs/_build/html/_sources/os.txt
docs/_build/html/_sources/resources.txt
docs/_build/html/_sources/start.txt
docs/_build/html/_sources/templates.txt
docs/_build/html/_sources/utils.txt
docs/_build/html/_sources/books/cmd_book.txt
docs/_build/html/_sources/books/index.txt
docs/_build/html/_sources/books/own_books.txt
docs/_build/html/_sources/os/linux.txt
docs/_build/html/_sources/os/windows.txt
pywizard/__init__.py
pywizard/alternatives.py
pywizard/api.py
pywizard/cli.py
pywizard/context.py
pywizard/events.py
pywizard/process.py
pywizard/resource.py
pywizard/templating.py
pywizard.egg-info/PKG-INFO
pywizard.egg-info/SOURCES.txt
pywizard.egg-info/dependency_links.txt
pywizard.egg-info/entry_points.txt
pywizard.egg-info/requires.txt
pywizard.egg-info/top_level.txt
pywizard/resources/__init__.py
pywizard/resources/_util_package_pip_.py
pywizard/resources/osutils.py
pywizard/resources/package_apt.py
pywizard/resources/package_pip.py
pywizard/resources/package_yum.py
pywizard/resources/resource_config.py
pywizard/resources/resource_file.py
pywizard/resources/resource_git.py
pywizard/resources/resource_package.py
pywizard/resources/resource_python.py
pywizard/resources/resource_service.py
pywizard/resources/resource_shell.py
pywizard/resources/resource_symlink.py
pywizard/resources/resource_user.py
pywizard/resources/resource_virtualenv.py
pywizard/resources/sudo.py
test/__init__.py
test/test_alternatives.py
test/test_cli.py
test/test_context.py
test/test_events.py
test/test_resource.py
test/test_resource_set.py
test/test_templating.py