Metadata-Version: 1.0
Name: pywizard
Version: 0.7.1
Summary: Tool that implements chef/puppet -like approach for server management.
Home-page: UNKNOWN
Author: Aleksandr Rudakov
Author-email: ribozz@gmail.com
License: MIT
Platform: UNKNOWN
